database_interface/__init__.py
database_interface/database.py
database_interface/postgis.py
database_interface/postgresql.py
database_interface/sqlite.py
database_interface/core/__init__.py
database_interface/core/column.py
database_interface/core/db_utils.py
database_interface/core/sql.py
database_interface/core/table.py
unnecessary_abstraction-1.3.5.dist-info/METADATA
unnecessary_abstraction-1.3.5.dist-info/WHEEL
unnecessary_abstraction-1.3.5.dist-info/top_level.txt
unnecessary_abstraction-1.3.5.dist-info/RECORD
