Metadata-Version: 2.4
Name: unnecessary-abstraction
Version: 1.3.5
Summary: For smooth brains who don't sql good.
Author-email: Michael Howard <michael.howard15123@gmail.com>
Classifier: License :: OSI Approved :: MIT License
Classifier: Programming Language :: Python :: 3.11
Classifier: Operating System :: OS Independent
Requires-Python: >=3.9
Requires-Dist: psycopg[binary]<4.0,>=3.1
Requires-Dist: psycopg-pool<4.0,>=3.1
